{
  "type": "vocab",
  "id": "bella-vista-1-4",
  "title": "Bella Vista 1 ch 4",
  "src": "it",
  "dst": "fi",
  "items": [
    { "id": "in-citta", "src": "in città", "dst": "kaupungilla" },
    { "id": "la-citta", "src": "la città", "dst": "kaupunki" },
    { "id": "raffreddato", "src": "raffreddato", "dst": "vilustunut" },
    { "id": "va", "src": "va", "dst": "menee" },
    { "id": "andare", "src": "andare", "dst": "mennä, käydä" },
    { "id": "la-confezione", "src": "la confezione", "dst": "pakkaus" },
    { "id": "in-farmacia", "src": "in farmacia", "dst": "apteekkiin, apteekissa" },
    { "id": "la-farmacia", "src": "la farmacia", "dst": "apteekki" },
    { "id": "l-aspirina", "src": "l’aspirina", "dst": "aspiriini, särkylääke" },
    { "id": "salute", "src": "Salute!", "dst": "Terveydeksi! (kun joku aivastaa)" },
    { "id": "questo-questa", "src": "questo, questa", "dst": "tämä" },
    { "id": "da-4-euro", "src": "da 4 euro", "dst": "4 euron hintainen" },
    { "id": "da", "src": "da", "dst": "jonkin hintainen" },
    { "id": "prendo", "src": "prendo", "dst": "otan" },
    { "id": "quello-quella", "src": "quello, quella", "dst": "tuo, se" },
    { "id": "il-cerotto", "src": "il cerotto", "dst": "laastari" },
    { "id": "vanno-bene", "src": "vanno bene", "dst": "käyvät (hyvin)" },
    { "id": "questi-queste", "src": "questi, queste", "dst": "nämä" },
    { "id": "quelli-quelle", "src": "quelli, quelle", "dst": "nuo, ne" },
    { "id": "altro", "src": "Altro?", "dst": "Saako olla muuta?" },
    { "id": "no-grazie-basta-cosi", "src": "No, grazie, basta così.", "dst": "Ei kiitos, näin riittää." },
    { "id": "in-tutto-fa", "src": "In tutto fa…", "dst": "Yhteensä se tekee…" },
    { "id": "in-tutto", "src": "in tutto", "dst": "yhteensä" },
    { "id": "per-strada", "src": "per strada", "dst": "kadulla" },
    { "id": "la-strada", "src": "la strada", "dst": "katu" },
    { "id": "un-suo-amico", "src": "un suo amico", "dst": "eräs hänen ystävänsä" },
    { "id": "suo", "src": "suo", "dst": "hänen" },
    { "id": "in-piazza", "src": "in piazza", "dst": "aukiolla" },
    { "id": "la-piazza", "src": "la piazza", "dst": "aukio" },
    { "id": "vanno", "src": "vanno", "dst": "menevät" },
    { "id": "verso", "src": "verso", "dst": "kohti, päin" },
    { "id": "la-tabaccheria", "src": "la tabaccheria", "dst": "tupakkakauppa" },
    { "id": "devo", "src": "devo", "dst": "minun täytyy" },
    { "id": "dovere", "src": "dovere", "dst": "täytyä" },
    { "id": "andare-a-comprare", "src": "andare a comprare", "dst": "mennä ostamaan" },
    { "id": "in-tabaccheria", "src": "in tabaccheria", "dst": "tupakkakauppaan, tupakkakaupassa" },
    { "id": "il-francobollo", "src": "il francobollo", "dst": "postimerkki" },
    { "id": "per", "src": "per", "dst": "jotakin varten" },
    { "id": "la-cartolina", "src": "la cartolina", "dst": "postikortti" },
    { "id": "chiuso", "src": "chiuso", "dst": "kiinni" },
    { "id": "e-vero", "src": "È vero.", "dst": "Se on totta." },
    { "id": "vero", "src": "vero", "dst": "tosi" },
    { "id": "peccato", "src": "Peccato!", "dst": "Harmi!" },
    { "id": "che-ore-sono", "src": "Che ore sono?", "dst": "Paljonko kello on?" },
    { "id": "l-ora", "src": "l’ora", "dst": "tunti" },
    { "id": "sono-le-dieci", "src": "Sono le dieci.", "dst": "Kello on kymmenen." },
    { "id": "ho-tempo-di-fare-un-salto-in-edicola", "src": "Ho tempo di fare un salto in edicola.", "dst": "Minulla on aikaa käydä lehtikioskilla." },
    { "id": "avere-tempo-di", "src": "avere tempo di", "dst": "olla aikaa tehdä jotakin" },
    { "id": "fare-un-salto", "src": "fare un salto", "dst": "pistäytyä jossakin" },
    { "id": "in-edicola", "src": "in edicola", "dst": "lehtikioskilla, lehtikioskille" },
    { "id": "l-edicola", "src": "l’edicola", "dst": "lehtikioski" },
    { "id": "poi", "src": "poi", "dst": "sitten" },
    { "id": "scappare", "src": "scappare", "dst": "lähteä (kiireesti)" },
    { "id": "devi", "src": "devi", "dst": "sinun täytyy" },
    { "id": "alle-undici", "src": "alle undici", "dst": "kello yhdeltätoista" },
    { "id": "alle", "src": "alle", "dst": "johonkin aikaan" },
    { "id": "cominciare", "src": "cominciare", "dst": "alkaa" },
    { "id": "la-lezione", "src": "la lezione", "dst": "luento, oppitunti" },
    { "id": "vai", "src": "vai", "dst": "menet" },
    { "id": "ora", "src": "ora", "dst": "nyt" },
    { "id": "vado", "src": "vado", "dst": "menen" },
    { "id": "verso-l-una", "src": "verso l’una", "dst": "kello yhden aikaan" },
    { "id": "prendi-l-autobus", "src": "Prendi l’autobus?", "dst": "Menetkö bussilla?" },
    { "id": "prendere-kulkuneuvo", "src": "prendere", "dst": "mennä jollakin kulkuneuvolla" },
    { "id": "l-autobus", "src": "l’autobus", "dst": "bussi" },
    { "id": "andare-con-l-autobus", "src": "andare con l’autobus", "dst": "mennä bussilla" },
    { "id": "con", "src": "con", "dst": "jollakin kulkuneuvolla" },
    { "id": "prendo-il-450", "src": "Prendo il 450.", "dst": "Menen bussilla numero 450." },
    { "id": "il-corriere", "src": "il Corriere", "dst": "eräs italialainen sanomalehti" },
    { "id": "il-biglietto-per-l-autobus", "src": "il biglietto per l’autobus", "dst": "bussilippu" },
    { "id": "quanto-costa", "src": "Quanto costa?", "dst": "Paljonko maksaa?" },
    { "id": "quanto", "src": "quanto?", "dst": "paljonko?" },
    { "id": "costare", "src": "costare", "dst": "maksaa (hinnasta)" },
    { "id": "la-rivista", "src": "la rivista", "dst": "aikakauslehti" },
    { "id": "a-lei-il-resto-prego", "src": "A Lei il resto, prego.", "dst": "Tässä Teille vaihtorahat, olkaa hyvä." }
  ]
}

